autognosis/__init__.py
autognosis/__main__.py
autognosis/autognosis.py
autognosis/steer_dynamics.py
autognosis/utils.py
autognosis-0.1.0.dist-info/METADATA
autognosis-0.1.0.dist-info/WHEEL
autognosis-0.1.0.dist-info/entry_points.txt
autognosis-0.1.0.dist-info/RECORD
