Metadata-Version: 2.3
Name: autognosis
Version: 0.1.0
Summary: Add your description here
Author-email: todo <todo@todo.todo>
Requires-Python: >=3.10
Requires-Dist: autonomous-proto>=0.1.4
Requires-Dist: matplotlib>=3.10.5
Requires-Dist: pydantic>=2.11.7
Requires-Dist: pyside6>=6.9.2
Requires-Dist: questionary>=2.1.1
Requires-Dist: rosbags>=0.10.11
Requires-Dist: scipy>=1.15.3
Requires-Dist: typer>=0.16.1
